mlx_proxy/generate_step.py
mlx_proxy/samplers.py
mlx_proxy/tokenizer.py
mlx_proxy/utils.py
mlx_proxy/cache/__init__.py
mlx_proxy/cache/cache.py
mlx_proxy/cache/quantized.py
mlx_proxy/cache/reusable.py
mlx_proxy/cache/rotating.py
mlx_proxy/logits_processors/__init__.py
mlx_proxy/logits_processors/repetition.py
mlx_proxy/models/__init__.py
mlx_proxy/models/base.py
mlx_proxy/models/llama.py
mlx_proxy/models/rope_utils.py
mlx_proxy/models/su_rope.py
mlx_proxy/models/switch_layers.py
mlx_proxy-0.3.3.dist-info/METADATA
mlx_proxy-0.3.3.dist-info/WHEEL
mlx_proxy-0.3.3.dist-info/licenses/LICENSE
mlx_proxy-0.3.3.dist-info/RECORD
