Metadata-Version: 2.4
Name: mlx-proxy
Version: 0.3.3
Summary: MLX optimized for The Proxy Company's use cases
Project-URL: homepage, https://github.com/TheProxyCompany/mlx-proxy
Project-URL: documentation, https://github.com/TheProxyCompany/mlx-proxy
Project-URL: source, https://github.com/TheProxyCompany/mlx-proxy
Author-email: Jack Wind <jckwind11@gmail.com>, The Proxy Company <contact@theproxy.company>
License:                                  Apache License
License-File: LICENSE
Requires-Python: >=3.8
Requires-Dist: flake8
Requires-Dist: jinja2
Requires-Dist: mlx
Requires-Dist: mlx-lm
Requires-Dist: numpy
Requires-Dist: protobuf
Requires-Dist: pyyaml
Requires-Dist: ruff
Requires-Dist: transformers[sentencepiece]
